{
  "node": {
    "60cb07c21ca64df01da29f053d9d442ce5a08422da": {
      "workers": {
        "app/page": {
          "moduleId": "[project]/.next-internal/server/app/page/actions.js { ACTIONS_MODULE0 => \"[project]/src/app/actions.ts [app-rsc] (ecmascript)\" } [app-rsc] (server actions loader, ecmascript)",
          "async": false
        }
      },
      "layer": {
        "app/page": "action-browser"
      }
    },
    "60077d5d82382de7ed9eec6d8a074fde6cf917f0bd": {
      "workers": {
        "app/page": {
          "moduleId": "[project]/.next-internal/server/app/page/actions.js { ACTIONS_MODULE0 => \"[project]/src/app/actions.ts [app-rsc] (ecmascript)\" } [app-rsc] (server actions loader, ecmascript)",
          "async": false
        }
      },
      "layer": {
        "app/page": "action-browser"
      }
    }
  },
  "edge": {},
  "encryptionKey": "oWXN5iR9nWbOd9ej5Td1tBl9+i0PgQVDFvpWCDCCK/U="
}